super_calculadora_e_KNUCKLES/__init__.py
super_calculadora_e_KNUCKLES/operations.py
super_calculadora_e_knuckles-0.1.1.dist-info/METADATA
super_calculadora_e_knuckles-0.1.1.dist-info/WHEEL
super_calculadora_e_knuckles-0.1.1.dist-info/top_level.txt
super_calculadora_e_knuckles-0.1.1.dist-info/RECORD
