Metadata-Version: 2.4
Name: super_calculadora_e_KNUCKLES
Version: 0.1.1
Summary: Biblioteca BASICA.
Home-page: https://github.com/RafaelDeps/testes_Lib
Author: Rafael Deps 
Author-email: rafaeldeps15@gmail.com
Classifier: Programming Language :: Python :: 3
Classifier: License :: OSI Approved :: MIT License
Classifier: Operating System :: OS Independent
Requires-Python: >=3.8
Dynamic: author
Dynamic: author-email
Dynamic: classifier
Dynamic: description
Dynamic: description-content-type
Dynamic: home-page
Dynamic: requires-python
Dynamic: summary
